NumerosPrimos_Leccion4/__init__.py
NumerosPrimos_Leccion4-1.0.dist-info/LICENSE.txt
NumerosPrimos_Leccion4-1.0.dist-info/METADATA
NumerosPrimos_Leccion4-1.0.dist-info/WHEEL
NumerosPrimos_Leccion4-1.0.dist-info/top_level.txt
NumerosPrimos_Leccion4-1.0.dist-info/RECORD
